PyTumblr-0.0.8.dist-info/METADATA
PyTumblr-0.0.8.dist-info/RECORD
PyTumblr-0.0.8.dist-info/WHEEL
PyTumblr-0.0.8.dist-info/top_level.txt
pytumblr/__init__.py
pytumblr/helpers.py
pytumblr/request.py
