Metadata-Version: 2.1
Name: PyTumblr
Version: 0.0.8
Summary: A Python API v2 wrapper for Tumblr
Home-page: https://github.com/tumblr/pytumblr
Author: Tumblr
Author-email: accounts@tumblr.com
License: Apache Software License 2.0
Download-URL: https://github.com/tumblr/pytumblr/archive/0.0.8.tar.gz
Keywords: pytumblr
Platform: UNKNOWN
Classifier: Development Status :: 4 - Beta
Classifier: Intended Audience :: Developers
Classifier: License :: OSI Approved :: Apache Software License
Classifier: Natural Language :: English
Classifier: Programming Language :: Python :: 2
Classifier: Programming Language :: Python :: 2.6
Classifier: Programming Language :: Python :: 2.7
Classifier: Programming Language :: Python :: 3
Classifier: Programming Language :: Python :: 3.3
Classifier: Programming Language :: Python :: 3.4
Classifier: Programming Language :: Python :: 3.5
Classifier: Programming Language :: Python :: 3.6
Requires-Dist: future
Requires-Dist: requests-oauthlib
